rest_filters/__init__.py
rest_filters/backends.py
rest_filters/conf.py
rest_filters/constraints.py
rest_filters/fields.py
rest_filters/filters.py
rest_filters/filtersets.py
rest_filters/locale/de/LC_MESSAGES/django.mo
rest_filters/locale/de/LC_MESSAGES/django.po
rest_filters/locale/tr/LC_MESSAGES/django.mo
rest_filters/locale/tr/LC_MESSAGES/django.po
rest_filters/py.typed
rest_filters/utils.py
rest_filters-0.7.0.dist-info/WHEEL
rest_filters-0.7.0.dist-info/METADATA
rest_filters-0.7.0.dist-info/RECORD
