Metadata-Version: 2.3
Name: rest-filters
Version: 0.7.0
Summary: A filter backend for Django REST framework.
Author: şuayip üzülmez
Author-email: şuayip üzülmez <suayip.541@gmail.com>
License: Copyright (c) 2025, Şuayip Üzülmez
Classifier: License :: OSI Approved :: BSD License
Classifier: Environment :: Web Environment
Classifier: Framework :: Django
Classifier: Framework :: Django :: 4.2
Classifier: Framework :: Django :: 5.2
Classifier: Programming Language :: Python
Classifier: Programming Language :: Python :: 3
Classifier: Programming Language :: Python :: 3.10
Classifier: Programming Language :: Python :: 3.11
Classifier: Programming Language :: Python :: 3.12
Classifier: Programming Language :: Python :: 3.13
Classifier: Programming Language :: Python :: 3.14
Requires-Dist: django>=4.2
Requires-Dist: djangorestframework>=3.14
Requires-Python: >=3.10
Project-URL: Bug Tracker, https://github.com/realsuayip/rest-filters/issues
Project-URL: Homepage, https://github.com/realsuayip/rest-filters
